speeed/__init__.py
speeed/speeed.py
speeed-1.0.1.dist-info/DESCRIPTION.rst
speeed-1.0.1.dist-info/METADATA
speeed-1.0.1.dist-info/RECORD
speeed-1.0.1.dist-info/WHEEL
speeed-1.0.1.dist-info/entry_points.txt
speeed-1.0.1.dist-info/metadata.json
speeed-1.0.1.dist-info/top_level.txt
